stupid/__init__.py
stupid/meta.py
stupid-1.1.0.dist-info/LICENSE
stupid-1.1.0.dist-info/METADATA
stupid-1.1.0.dist-info/WHEEL
stupid-1.1.0.dist-info/top_level.txt
stupid-1.1.0.dist-info/RECORD
