Metadata-Version: 2.1
Name: stupid
Version: 1.1.0
Summary: Support for multiple inheritance and __slots__
Home-page: https://github.com/masell/stupid
Author: masell
License: BSD
Platform: UNKNOWN
Classifier: Development Status :: 4 - Beta
Classifier: License :: OSI Approved :: BSD License
Classifier: Programming Language :: Python :: 3.6
Classifier: Programming Language :: Python :: 3.7
Classifier: Intended Audience :: Developers
Classifier: Operating System :: OS Independent
Requires-Dist: dataclasses
